gym_bandits/__init__.py
gym_bandits/envs/__init__.py
gym_bandits/envs/bandits_env.py
gym_bandits-0.0.1.dist-info/LICENSE
gym_bandits-0.0.1.dist-info/METADATA
gym_bandits-0.0.1.dist-info/WHEEL
gym_bandits-0.0.1.dist-info/top_level.txt
gym_bandits-0.0.1.dist-info/RECORD
