Metadata-Version: 2.1
Name: gym-bandits
Version: 0.0.1
Summary: Implements multi-armed bandits
Home-page: https://github.com/magni84/gym_bandits
Author: Per Mattsson
Author-email: magni84@gmail.com
License: UNKNOWN
Platform: UNKNOWN
Classifier: Programming Language :: Python :: 3
Classifier: License :: OSI Approved :: MIT License
Classifier: Operating System :: OS Independent
Requires-Dist: gym
Requires-Dist: numpy
